pyGeckoCrypto/__init__.py
pyGeckoCrypto/api.py
pyGeckoCrypto/custom_exception.py
pyGeckoCrypto/logger.py
pyGeckoCrypto-0.0.3.dist-info/LICENSE
pyGeckoCrypto-0.0.3.dist-info/METADATA
pyGeckoCrypto-0.0.3.dist-info/WHEEL
pyGeckoCrypto-0.0.3.dist-info/top_level.txt
pyGeckoCrypto-0.0.3.dist-info/RECORD
