Metadata-Version: 2.1
Name: pyGeckoCrypto
Version: 0.0.3
Summary: A wrapper for the CoinGecko API to fetch prices and historical data
Home-page: https://github.com/abealexander/pyGeckoCrypto
Author: abealexander
Author-email: abealexander07@gmail.com
License: MIT
Project-URL: Bug Tracker, https://github.com/abealexander/pyGeckoCrypto/issues
Classifier: Programming Language :: Python :: 3.7
Classifier: Programming Language :: Python :: 3.8
Classifier: Programming Language :: Python :: 3.9
Classifier: Operating System :: OS Independent
Requires-Python: >=3.7
License-File: LICENSE
Requires-Dist: requests (==2.28.1)
Requires-Dist: types-requests (==2.28.11.1)
Requires-Dist: ensure (==1.0.2)
Provides-Extra: testing
Requires-Dist: pytest (>=7.1.3) ; extra == 'testing'
Requires-Dist: mypy (>=0.971) ; extra == 'testing'
Requires-Dist: flake8 (>=5.0.4) ; extra == 'testing'
Requires-Dist: tox (>=3.25.1) ; extra == 'testing'
Requires-Dist: black (>=22.8.0) ; extra == 'testing'
